JABWrapper/context_tree.py
JABWrapper/context_tree_reader.py
JABWrapper/jab_types.py
JABWrapper/jab_wrapper.py
JABWrapper/parsers/actions_parser.py
JABWrapper/parsers/hypertext_parser.py
JABWrapper/parsers/icon_parser.py
JABWrapper/parsers/keybind_parser.py
JABWrapper/parsers/parser_if.py
JABWrapper/parsers/selection_parser.py
JABWrapper/parsers/table_parser.py
JABWrapper/parsers/text_parser.py
JABWrapper/parsers/value_parser.py
JABWrapper/utils.py
java_access_bridge_wrapper-1.1.0.dist-info/LICENSE
java_access_bridge_wrapper-1.1.0.dist-info/METADATA
java_access_bridge_wrapper-1.1.0.dist-info/WHEEL
java_access_bridge_wrapper-1.1.0.dist-info/entry_points.txt
java_access_bridge_wrapper-1.1.0.dist-info/RECORD
