Metadata-Version: 2.1
Name: java-access-bridge-wrapper
Version: 1.1.0
Summary: Python wrapper for the Windows Java Access Bridge
Home-page: https://github.com/robocorp/java-access-bridge-wrapper.git
License: Apache-2.0
Author: Robocorp
Author-email: support@robocorp.com
Requires-Python: >=3.8.1,<4.0.0
Classifier: Development Status :: 4 - Beta
Classifier: Intended Audience :: Developers
Classifier: License :: OSI Approved :: Apache Software License
Classifier: Operating System :: Microsoft :: Windows
Classifier: Programming Language :: Python :: 3
Classifier: Programming Language :: Python :: 3.9
Classifier: Programming Language :: Python :: 3.10
Classifier: Programming Language :: Python :: 3.11
Classifier: Programming Language :: Python :: 3.8
Requires-Dist: pywin32 (>=300,<307) ; python_full_version != "3.8.1" and sys_platform == "win32"
Project-URL: Repository, https://github.com/robocorp/java-access-bridge-wrapper.git
